__init__.py
dlo.py
dlo_vgenovpy-1.0.0.dist-info/LICENSE
dlo_vgenovpy-1.0.0.dist-info/METADATA
dlo_vgenovpy-1.0.0.dist-info/WHEEL
dlo_vgenovpy-1.0.0.dist-info/top_level.txt
dlo_vgenovpy-1.0.0.dist-info/RECORD
