Metadata-Version: 2.1
Name: dlo-vgenovpy
Version: 1.0.0
Summary: Query SQLite databases with ease and with dicts
Author-email: vgenovpy <genovese.work@eprotonmail.com>
Project-URL: Homepage, https://github.com/vgenov-py/dlo
Classifier: Programming Language :: Python :: 3
Classifier: License :: OSI Approved :: MIT License
Classifier: Operating System :: OS Independent
Requires-Python: >=3.9
License-File: LICENSE
